COG/COG.py
COG/__init__.py
COG/cognames2003-2014.tab
COG/fun2003-2014.tab
COG_translator-0.0.21.dist-info/LICENSE.txt
COG_translator-0.0.21.dist-info/METADATA
COG_translator-0.0.21.dist-info/WHEEL
COG_translator-0.0.21.dist-info/top_level.txt
COG_translator-0.0.21.dist-info/RECORD
