Metadata-Version: 2.1
Name: COG-translator
Version: 0.0.21
Summary: COG-translator, a pure Python translator for COG names.
Home-page: UNKNOWN
Author: Vini Salazar
Author-email: viniws@gmail.com
License: UNKNOWN
Platform: UNKNOWN
